avrotize/__init__.py
avrotize/__main__.py
avrotize/_version.py
avrotize/asn1toavro.py
avrotize/avrotize.py
avrotize/avrotocpp.py
avrotize/avrotocsharp.py
avrotize/avrotocsv.py
avrotize/avrotodatapackage.py
avrotize/avrotodb.py
avrotize/avrotogo.py
avrotize/avrotographql.py
avrotize/avrotoiceberg.py
avrotize/avrotojava.py
avrotize/avrotojs.py
avrotize/avrotojsons.py
avrotize/avrotojstruct.py
avrotize/avrotokusto.py
avrotize/avrotomd.py
avrotize/avrotools.py
avrotize/avrotoparquet.py
avrotize/avrotoproto.py
avrotize/avrotopython.py
avrotize/avrotorust.py
avrotize/avrotots.py
avrotize/avrotoxsd.py
avrotize/cddltostructure.py
avrotize/commands.json
avrotize/common.py
avrotize/constants.py
avrotize/csvtoavro.py
avrotize/datapackagetoavro.py
avrotize/dependency_resolver.py
avrotize/dependency_version.py
avrotize/jsonstoavro.py
avrotize/jsonstostructure.py
avrotize/jstructtoavro.py
avrotize/kstructtoavro.py
avrotize/kustotoavro.py
avrotize/openapitostructure.py
avrotize/parquettoavro.py
avrotize/proto2parser.py
avrotize/proto3parser.py
avrotize/prototoavro.py
avrotize/structuretocddl.py
avrotize/structuretocpp.py
avrotize/structuretocsharp.py
avrotize/structuretocsv.py
avrotize/structuretodatapackage.py
avrotize/structuretodb.py
avrotize/structuretogo.py
avrotize/structuretographql.py
avrotize/structuretoiceberg.py
avrotize/structuretojava.py
avrotize/structuretojs.py
avrotize/structuretojsons.py
avrotize/structuretokusto.py
avrotize/structuretomd.py
avrotize/structuretoproto.py
avrotize/structuretopython.py
avrotize/structuretorust.py
avrotize/structuretots.py
avrotize/structuretoxsd.py
avrotize/xsdtoavro.py
avrotize/dependencies/cpp/vcpkg/vcpkg.json
avrotize/dependencies/typescript/node22/package.json
structurize-3.0.2.dist-info/licenses/LICENSE
structurize-3.0.2.dist-info/METADATA
structurize-3.0.2.dist-info/WHEEL
structurize-3.0.2.dist-info/entry_points.txt
structurize-3.0.2.dist-info/top_level.txt
structurize-3.0.2.dist-info/RECORD
